[
    { 
 	    "id": "vli",
	    "name": "Vicki Li", 
        "age": 20, 
	"height": 52,
        "school": "University of Michigan",
        "oneLiner": "Flying Purple Jelly Hippo Waffle",
        "additional":
        [
            {
                "category": "skills",
                "text": "C++\nSQL"
            },
            {
                "category": "hobbies",
                "text": "I enjoy doing cosplay and steampunk stuff\nI also enjoy playing LoL"
            }
        ]   
    }, 
    {
        "id": "smartinez", 
        "name": "Sebastian Martinez", 
        "age": 22, 
	"height": 62,
        "school": "University of Michigan",
        "oneLiner": "Hippos Fly West",
        "additional":
        [
            {
                "category": "skills",
                "text": "C++\nSQL"
            },
            {
                "category": "hobbies",
                "text": "I enjoy Legos\nI also enjoy playing LoL"
            }
        ]
    }, 
    {
        "id": "chejazi", 
        "name": "Cameron Hejazi", 
        "age": 21, 
	"height": 63,
        "school": "University of Michigan",
        "oneLiner": "Chicken Can Fly in Space",
        "additional":
        [
            {
                "category": "skills",
                "text": "C++\nstuff"
            },
            {
                "category": "hobbies",
                "text": "Music is my thing\nI love eating pizza"
            }
        ]
    }, 
    {
        "id": "arajagopal", 
        "name": "Aditi Rajagopal", 
        "age": 21, 
	"height": 51,
        "school": "University of Michigan",
        "oneLiner": "I can FLY!",
        "additional":
        [
            {
                "category": "skills",
                "text": "C++\nCSE"
            },
            {
                "category": "hobbies",
                "text": "I enjoy singing\nI also enjoy hiking"
            }
        ] 
    }
]
